LICENSE
perceiver_pytorch/__init__.py
perceiver_pytorch/caching.py
perceiver_pytorch/common.py
perceiver_pytorch/experimental.py
perceiver_pytorch/gated.py
perceiver_pytorch/hierarchical_multi_modality_perceiver.py
perceiver_pytorch/modalities.py
perceiver_pytorch/multi_modality_perceiver.py
perceiver_pytorch/multi_modality_with_text_perceiver.py
perceiver_pytorch/perceiver_pytorch.py
perceiver_multi_modality_pytorch-1.4.0.dist-info/LICENSE
perceiver_multi_modality_pytorch-1.4.0.dist-info/WHEEL
perceiver_multi_modality_pytorch-1.4.0.dist-info/METADATA
perceiver_multi_modality_pytorch-1.4.0.dist-info/RECORD
