Metadata-Version: 2.1
Name: perceiver-multi-modality-pytorch
Version: 1.4.0
Summary: A fork of perceiver-pytorch that supports multiple modalities for the Perceiver architecture.
Home-page: https://github.com/fac2003/perceiver-multi-modality-pytorch
License: MIT
Keywords: machine learning,perceiver,pytorch,multi-modality,image,video,text,audio
Author: Fabien Campagne
Author-email: fac2003@gmail.com
Requires-Python: >=3.7,<4.0
Classifier: Development Status :: 4 - Beta
Classifier: Intended Audience :: Developers
Classifier: License :: OSI Approved :: MIT License
Classifier: Operating System :: OS Independent
Classifier: Programming Language :: Python :: 3
Classifier: Programming Language :: Python :: 3.7
Classifier: Programming Language :: Python :: 3.8
Classifier: Programming Language :: Python :: 3.9
Classifier: Topic :: Scientific/Engineering
Classifier: Topic :: Scientific/Engineering :: Artificial Intelligence
Requires-Dist: einops (>=0.3,<0.4)
Requires-Dist: torch (>=1.6.0,<2.0.0)
Project-URL: Repository, https://github.com/fac2003/perceiver-multi-modality-pytorch
